hex_utility_pkg/__init__.py
hex_utility_pkg/calsum.py
hex_utility_pkg/spilt_string.py
hex_utility_pkg-0.0.2.dist-info/METADATA
hex_utility_pkg-0.0.2.dist-info/WHEEL
hex_utility_pkg-0.0.2.dist-info/top_level.txt
hex_utility_pkg-0.0.2.dist-info/RECORD
