Metadata-Version: 2.1
Name: hex-utility-pkg
Version: 0.0.2
Requires-Dist: requests
Requires-Dist: importlib-metadata ; python_version > "3.8"
